[{"m_iID":1,"m_iValue":40},{"m_iID":2,"m_iValue":60029001},{"m_iID":3,"m_iValue":60029002},{"m_iID":4,"m_iValue":60029003},{"m_iID":5,"m_iValue":60029004},{"m_iID":6,"m_iValue":60029005},{"m_iID":7,"m_iValue":60029006},{"m_iID":8,"m_iValue":60029007},{"m_iID":9,"m_iValue":10000},{"m_iID":10,"m_iValue":51005455},{"m_iID":11,"m_iValue":10},{"m_iID":12,"m_iValue":1412265660},{"m_iID":13,"m_iValue":1},{"m_iID":14,"m_iValue":1},{"m_iID":15,"m_iValue":60029008},{"m_iID":16,"m_iValue":60029009},{"m_iID":19,"m_iValue":500},{"m_iID":20,"m_iValue":50},{"m_iID":21,"m_iValue":50},{"m_iID":22,"m_iValue":4},{"m_iID":23,"m_iValue":20},{"m_iID":24,"m_iValue":20},{"m_iID":25,"m_iValue":15},{"m_iID":26,"m_iValue":10},{"m_iID":27,"m_iValue":50},{"m_iID":28,"m_iValue":10},{"m_iID":29,"m_iValue":3},{"m_iID":30,"m_iValue":50},{"m_iID":31,"m_iValue":2},{"m_iID":32,"m_iValue":5},{"m_iID":33,"m_iValue":80000},{"m_iID":34,"m_iValue":1},{"m_iID":35,"m_iValue":2},{"m_iID":36,"m_iValue":10109011},{"m_iID":37,"m_iValue":10109021},{"m_iID":38,"m_iValue":10109031},{"m_iID":39,"m_iValue":10109041},{"m_iID":40,"m_iValue":10109051},{"m_iID":41,"m_iValue":10109061},{"m_iID":42,"m_iValue":1},{"m_iID":43,"m_iValue":80},{"m_iID":44,"m_iValue":1},{"m_iID":45,"m_iValue":100},{"m_iID":46,"m_iValue":50000},{"m_iID":47,"m_iValue":31000021},{"m_iID":48,"m_iValue":3000},{"m_iID":49,"m_iValue":30001057},{"m_iID":50,"m_iValue":1},{"m_iID":51,"m_iValue":1},{"m_iID":52,"m_iValue":1},{"m_iID":53,"m_iValue":10},{"m_iID":54,"m_iValue":5},{"m_iID":55,"m_iValue":1},{"m_iID":56,"m_iValue":1},{"m_iID":57,"m_iValue":5},{"m_iID":58,"m_iValue":2},{"m_iID":59,"m_iValue":22},{"m_iID":60,"m_iValue":28},{"m_iID":61,"m_iValue":22},{"m_iID":62,"m_iValue":15},{"m_iID":63,"m_iValue":5},{"m_iID":64,"m_iValue":20},{"m_iID":65,"m_iValue":18},{"m_iID":66,"m_iValue":16},{"m_iID":67,"m_iValue":14},{"m_iID":68,"m_iValue":12},{"m_iID":69,"m_iValue":15},{"m_iID":70,"m_iValue":1},{"m_iID":71,"m_iValue":200},{"m_iID":72,"m_iValue":6000},{"m_iID":73,"m_iValue":500},{"m_iID":74,"m_iValue":1},{"m_iID":75,"m_iValue":100},{"m_iID":76,"m_iValue":588},{"m_iID":88,"m_iValue":8},{"m_iID":89,"m_iValue":2},{"m_iID":90,"m_iValue":500},{"m_iID":91,"m_iValue":10000},{"m_iID":92,"m_iValue":300},{"m_iID":93,"m_iValue":5},{"m_iID":94,"m_iValue":5},{"m_iID":95,"m_iValue":50},{"m_iID":96,"m_iValue":3344},{"m_iID":97,"m_iValue":998},{"m_iID":98,"m_iValue":1314},{"m_iID":99,"m_iValue":1001031},{"m_iID":106,"m_iValue":20},{"m_iID":107,"m_iValue":90},{"m_iID":108,"m_iValue":190},{"m_iID":109,"m_iValue":1},{"m_iID":110,"m_iValue":180},{"m_iID":111,"m_iValue":240},{"m_iID":112,"m_iValue":300},{"m_iID":113,"m_iValue":300},{"m_iID":114,"m_iValue":300},{"m_iID":115,"m_iValue":180},{"m_iID":116,"m_iValue":120},{"m_iID":117,"m_iValue":50},{"m_iID":118,"m_iValue":10},{"m_iID":119,"m_iValue":5},{"m_iID":120,"m_iValue":1},{"m_iID":121,"m_iValue":1},{"m_iID":122,"m_iValue":20},{"m_iID":123,"m_iValue":5},{"m_iID":124,"m_iValue":1},{"m_iID":125,"m_iValue":1},{"m_iID":126,"m_iValue":1},{"m_iID":127,"m_iValue":3},{"m_iID":128,"m_iValue":950},{"m_iID":129,"m_iValue":5},{"m_iID":130,"m_iValue":50},{"m_iID":131,"m_iValue":20},{"m_iID":132,"m_iValue":10},{"m_iID":133,"m_iValue":23},{"m_iID":134,"m_iValue":96},{"m_iID":135,"m_iValue":3},{"m_iID":136,"m_iValue":10},{"m_iID":137,"m_iValue":3600},{"m_iID":138,"m_iValue":20},{"m_iID":139,"m_iValue":7200},{"m_iID":140,"m_iValue":8000},{"m_iID":141,"m_iValue":6},{"m_iID":142,"m_iValue":1},{"m_iID":143,"m_iValue":50},{"m_iID":144,"m_iValue":10349061},{"m_iID":145,"m_iValue":10349051},{"m_iID":146,"m_iValue":60403116},{"m_iID":147,"m_iValue":60403117},{"m_iID":148,"m_iValue":1000},{"m_iID":149,"m_iValue":388},{"m_iID":150,"m_iValue":20},{"m_iID":151,"m_iValue":100},{"m_iID":152,"m_iValue":180},{"m_iID":153,"m_iValue":250},{"m_iID":154,"m_iValue":10},{"m_iID":155,"m_iValue":10},{"m_iID":156,"m_iValue":1000},{"m_iID":157,"m_iValue":60},{"m_iID":158,"m_iValue":100},{"m_iID":159,"m_iValue":220023},{"m_iID":160,"m_iValue":1000},{"m_iID":161,"m_iValue":50},{"m_iID":162,"m_iValue":150},{"m_iID":163,"m_iValue":250},{"m_iID":164,"m_iValue":20},{"m_iID":165,"m_iValue":259200},{"m_iID":166,"m_iValue":12500},{"m_iID":167,"m_iValue":1000},{"m_iID":168,"m_iValue":10},{"m_iID":169,"m_iValue":100},{"m_iID":170,"m_iValue":500},{"m_iID":171,"m_iValue":10027011},{"m_iID":172,"m_iValue":200},{"m_iID":173,"m_iValue":15},{"m_iID":174,"m_iValue":0},{"m_iID":175,"m_iValue":0},{"m_iID":178,"m_iValue":10},{"m_iID":179,"m_iValue":5},{"m_iID":180,"m_iValue":20},{"m_iID":181,"m_iValue":50},{"m_iID":182,"m_iValue":25},{"m_iID":183,"m_iValue":100},{"m_iID":184,"m_iValue":40},{"m_iID":185,"m_iValue":5},{"m_iID":186,"m_iValue":10},{"m_iID":187,"m_iValue":180},{"m_iID":188,"m_iValue":3},{"m_iID":189,"m_iValue":182},{"m_iID":190,"m_iValue":2000},{"m_iID":191,"m_iValue":10000},{"m_iID":192,"m_iValue":50000},{"m_iID":193,"m_iValue":12000},{"m_iID":194,"m_iValue":14400},{"m_iID":195,"m_iValue":21600},{"m_iID":196,"m_iValue":20000},{"m_iID":197,"m_iValue":2000},{"m_iID":198,"m_iValue":10000},{"m_iID":199,"m_iValue":60168024},{"m_iID":200,"m_iValue":60168025},{"m_iID":201,"m_iValue":60168026},{"m_iID":202,"m_iValue":10403021},{"m_iID":203,"m_iValue":10403011},{"m_iID":204,"m_iValue":888},{"m_iID":205,"m_iValue":200},{"m_iID":206,"m_iValue":60},{"m_iID":207,"m_iValue":5},{"m_iID":208,"m_iValue":5},{"m_iID":209,"m_iValue":30},{"m_iID":210,"m_iValue":60},{"m_iID":211,"m_iValue":288},{"m_iID":212,"m_iValue":1350},{"m_iID":213,"m_iValue":552},{"m_iID":214,"m_iValue":2640},{"m_iID":215,"m_iValue":100},{"m_iID":216,"m_iValue":900},{"m_iID":217,"m_iValue":60165023},{"m_iID":218,"m_iValue":30},{"m_iID":222,"m_iValue":10},{"m_iID":223,"m_iValue":3},{"m_iID":224,"m_iValue":5365},{"m_iID":225,"m_iValue":3557},{"m_iID":227,"m_iValue":1},{"m_iID":228,"m_iValue":35},{"m_iID":229,"m_iValue":2},{"m_iID":230,"m_iValue":0},{"m_iID":231,"m_iValue":4},{"m_iID":232,"m_iValue":4070},{"m_iID":233,"m_iValue":2735},{"m_iID":235,"m_iValue":4},{"m_iID":236,"m_iValue":92},{"m_iID":237,"m_iValue":16},{"m_iID":238,"m_iValue":20},{"m_iID":239,"m_iValue":20},{"m_iID":240,"m_iValue":30},{"m_iID":241,"m_iValue":1},{"m_iID":242,"m_iValue":460},{"m_iID":243,"m_iValue":3320},{"m_iID":244,"m_iValue":180},{"m_iID":245,"m_iValue":4},{"m_iID":246,"m_iValue":4070},{"m_iID":247,"m_iValue":2735},{"m_iID":250,"m_iValue":100},{"m_iID":251,"m_iValue":290},{"m_iID":252,"m_iValue":90},{"m_iID":253,"m_iValue":0},{"m_iID":254,"m_iValue":0},{"m_iID":255,"m_iValue":270},{"m_iID":256,"m_iValue":270},{"m_iID":257,"m_iValue":120},{"m_iID":258,"m_iValue":120},{"m_iID":259,"m_iValue":330},{"m_iID":260,"m_iValue":0},{"m_iID":261,"m_iValue":0},{"m_iID":262,"m_iValue":50},{"m_iID":263,"m_iValue":50},{"m_iID":264,"m_iValue":0},{"m_iID":268,"m_iValue":350},{"m_iID":269,"m_iValue":350},{"m_iID":270,"m_iValue":1000},{"m_iID":271,"m_iValue":800},{"m_iID":272,"m_iValue":400},{"m_iID":273,"m_iValue":1000},{"m_iID":274,"m_iValue":1000},{"m_iID":275,"m_iValue":1000},{"m_iID":276,"m_iValue":1000},{"m_iID":277,"m_iValue":1000},{"m_iID":278,"m_iValue":1000},{"m_iID":279,"m_iValue":1000},{"m_iID":280,"m_iValue":1000},{"m_iID":284,"m_iValue":10},{"m_iID":285,"m_iValue":2},{"m_iID":286,"m_iValue":10000011},{"m_iID":287,"m_iValue":40000006},{"m_iID":289,"m_iValue":3700},{"m_iID":290,"m_iValue":40000004},{"m_iID":291,"m_iValue":154506001},{"m_iID":292,"m_iValue":67},{"m_iID":293,"m_iValue":40000008},{"m_iID":294,"m_iValue":158509001},{"m_iID":295,"m_iValue":10000002},{"m_iID":296,"m_iValue":42},{"m_iID":297,"m_iValue":80},{"m_iID":298,"m_iValue":70},{"m_iID":299,"m_iValue":999},{"m_iID":300,"m_iValue":50},{"m_iID":301,"m_iValue":600},{"m_iID":302,"m_iValue":100},{"m_iID":303,"m_iValue":100},{"m_iID":304,"m_iValue":50},{"m_iID":305,"m_iValue":10},{"m_iID":306,"m_iValue":5000},{"m_iID":307,"m_iValue":160000},{"m_iID":308,"m_iValue":6000},{"m_iID":309,"m_iValue":1},{"m_iID":310,"m_iValue":30},{"m_iID":311,"m_iValue":0},{"m_iID":312,"m_iValue":10233011},{"m_iID":313,"m_iValue":0},{"m_iID":314,"m_iValue":100},{"m_iID":315,"m_iValue":100},{"m_iID":316,"m_iValue":5},{"m_iID":317,"m_iValue":60730001},{"m_iID":318,"m_iValue":31480002},{"m_iID":319,"m_iValue":31480003},{"m_iID":320,"m_iValue":31480004},{"m_iID":321,"m_iValue":60730002},{"m_iID":322,"m_iValue":2},{"m_iID":323,"m_iValue":100},{"m_iID":324,"m_iValue":1000},{"m_iID":325,"m_iValue":60},{"m_iID":326,"m_iValue":30},{"m_iID":328,"m_iValue":46800},{"m_iID":329,"m_iValue":61200},{"m_iID":333,"m_iValue":5000},{"m_iID":334,"m_iValue":10},{"m_iID":335,"m_iValue":9},{"m_iID":336,"m_iValue":3600},{"m_iID":337,"m_iValue":81},{"m_iID":338,"m_iValue":54},{"m_iID":340,"m_iValue":20},{"m_iID":341,"m_iValue":1},{"m_iID":342,"m_iValue":5000},{"m_iID":343,"m_iValue":20},{"m_iID":344,"m_iValue":20},{"m_iID":345,"m_iValue":20},{"m_iID":346,"m_iValue":10},{"m_iID":347,"m_iValue":10},{"m_iID":348,"m_iValue":30},{"m_iID":349,"m_iValue":500},{"m_iID":350,"m_iValue":5},{"m_iID":351,"m_iValue":0},{"m_iID":352,"m_iValue":0},{"m_iID":353,"m_iValue":0},{"m_iID":354,"m_iValue":0},{"m_iID":355,"m_iValue":1000},{"m_iID":356,"m_iValue":1000},{"m_iID":362,"m_iValue":3600},{"m_iID":363,"m_iValue":15},{"m_iID":364,"m_iValue":15},{"m_iID":365,"m_iValue":3600},{"m_iID":366,"m_iValue":15},{"m_iID":367,"m_iValue":3},{"m_iID":368,"m_iValue":200},{"m_iID":369,"m_iValue":10000},{"m_iID":370,"m_iValue":43200},{"m_iID":371,"m_iValue":480},{"m_iID":372,"m_iValue":388},{"m_iID":373,"m_iValue":2000},{"m_iID":374,"m_iValue":666666},{"m_iID":375,"m_iValue":2},{"m_iID":376,"m_iValue":10},{"m_iID":377,"m_iValue":5},{"m_iID":378,"m_iValue":10},{"m_iID":379,"m_iValue":7200}]